SpringDataJpa215ReleaseZhongwenWendang/README.md
SpringDataJpa215ReleaseZhongwenWendang/__init__.py
SpringDataJpa215ReleaseZhongwenWendang/__main__.py
SpringDataJpa215ReleaseZhongwenWendang/file.epub
SpringDataJpa215ReleaseZhongwenWendang/index.html
SpringDataJpa215ReleaseZhongwenWendang/css/__init__.py
SpringDataJpa215ReleaseZhongwenWendang/css/annotations.css
SpringDataJpa215ReleaseZhongwenWendang/css/main.css
SpringDataJpa215ReleaseZhongwenWendang/css/normalize.css
SpringDataJpa215ReleaseZhongwenWendang/css/popup.css
SpringDataJpa215ReleaseZhongwenWendang/font/__init__.py
SpringDataJpa215ReleaseZhongwenWendang/font/fontello.eot
SpringDataJpa215ReleaseZhongwenWendang/font/fontello.svg
SpringDataJpa215ReleaseZhongwenWendang/font/fontello.ttf
SpringDataJpa215ReleaseZhongwenWendang/font/fontello.woff
SpringDataJpa215ReleaseZhongwenWendang/img/__init__.py
SpringDataJpa215ReleaseZhongwenWendang/img/annotator-glyph-sprite.png
SpringDataJpa215ReleaseZhongwenWendang/img/annotator-icon-sprite.png
SpringDataJpa215ReleaseZhongwenWendang/img/apple-touch-icon.png
SpringDataJpa215ReleaseZhongwenWendang/img/cancelfullscreen.png
SpringDataJpa215ReleaseZhongwenWendang/img/close.png
SpringDataJpa215ReleaseZhongwenWendang/img/fullscreen.png
SpringDataJpa215ReleaseZhongwenWendang/img/loader.gif
SpringDataJpa215ReleaseZhongwenWendang/img/menu-icon.png
SpringDataJpa215ReleaseZhongwenWendang/img/save.png
SpringDataJpa215ReleaseZhongwenWendang/img/saved.png
SpringDataJpa215ReleaseZhongwenWendang/img/settings-s.png
SpringDataJpa215ReleaseZhongwenWendang/img/settings.png
SpringDataJpa215ReleaseZhongwenWendang/img/star.png
SpringDataJpa215ReleaseZhongwenWendang/js/__init__.py
SpringDataJpa215ReleaseZhongwenWendang/js/epub.js
SpringDataJpa215ReleaseZhongwenWendang/js/epub.min.js
SpringDataJpa215ReleaseZhongwenWendang/js/epub.min.map
SpringDataJpa215ReleaseZhongwenWendang/js/hooks.min.js
SpringDataJpa215ReleaseZhongwenWendang/js/hooks.min.map
spring_data_jpa_2_1_5_release_zhongwen_wendang-2024.3.5.0.dist-info/METADATA
spring_data_jpa_2_1_5_release_zhongwen_wendang-2024.3.5.0.dist-info/WHEEL
spring_data_jpa_2_1_5_release_zhongwen_wendang-2024.3.5.0.dist-info/entry_points.txt
spring_data_jpa_2_1_5_release_zhongwen_wendang-2024.3.5.0.dist-info/top_level.txt
spring_data_jpa_2_1_5_release_zhongwen_wendang-2024.3.5.0.dist-info/RECORD
